README.rst
setup.cfg
setup.py
Flask_Potion.egg-info/PKG-INFO
Flask_Potion.egg-info/SOURCES.txt
Flask_Potion.egg-info/dependency_links.txt
Flask_Potion.egg-info/not-zip-safe
Flask_Potion.egg-info/pbr.json
Flask_Potion.egg-info/requires.txt
Flask_Potion.egg-info/top_level.txt
flask_potion/__init__.py
flask_potion/exceptions.py
flask_potion/fields.py
flask_potion/filters.py
flask_potion/instances.py
flask_potion/manager.py
flask_potion/natural_keys.py
flask_potion/reference.py
flask_potion/resource.py
flask_potion/routes.py
flask_potion/schema.py
flask_potion/signals.py
flask_potion/utils.py
flask_potion/contrib/__init__.py
flask_potion/contrib/alchemy/__init__.py
flask_potion/contrib/alchemy/fields.py
flask_potion/contrib/alchemy/filters.py
flask_potion/contrib/alchemy/manager.py
flask_potion/contrib/memory/__init__.py
flask_potion/contrib/memory/manager.py
flask_potion/contrib/mongoengine/__init__.py
flask_potion/contrib/mongoengine/filters.py
flask_potion/contrib/mongoengine/manager.py
flask_potion/contrib/peewee/__init__.py
flask_potion/contrib/peewee/filters.py
flask_potion/contrib/peewee/manager.py
flask_potion/contrib/principals/__init__.py
flask_potion/contrib/principals/needs.py
flask_potion/contrib/principals/permission.py